colorAlphabet/__init__.py
colorAlphabet/__version__.py
colorAlphabet-0.3.dist-info/METADATA
colorAlphabet-0.3.dist-info/WHEEL
colorAlphabet-0.3.dist-info/top_level.txt
colorAlphabet-0.3.dist-info/RECORD
