Metadata-Version: 2.1
Name: colorAlphabet
Version: 0.3
Summary: Use Paul Green-Armytage color alphabet to color text output to a terminal
Home-page: https://bitbucket.org/bvidmar/colorAlphabet
Author: Roberto Vidmar
Author-email: rvidmar@inogs.it
License: MIT
Platform: UNKNOWN
Classifier: Programming Language :: Python :: 3.4
Classifier: Programming Language :: Python :: 3.6
Classifier: License :: OSI Approved :: MIT License
Classifier: Operating System :: OS Independent
Requires-Dist: setuptools (>=39.0.1)
